{
    "errno": 0,
    "total": 72,
    "data": {
        "queryString": "*",
        "total": 72,
        "timestamp": 1559889433955,
        "list": [{
                "itemId": "5cdb9c03a7d03149b3e0de9e",
                "title": "摩飞 便携式榨汁机（双杯） MR9200",
                "stock": 998,
                "img": "http://p3.qhimg.com/dr/400_400_80/t011469ff6bdc1e4c77.png",
                "listTag": "0",
                "price": "248",
                "uploadSting": "05-15上新",
                "tuan_flag": 0,
                "forward_url": ""
            },
            {
                "itemId": "5cdbe27af759f165ded4a498",
                "title": "摩飞 旅行便携式电热水壶 316不锈钢 MR6080",
                "stock": 997,
                "img": "http://p6.qhimg.com/dr/400_400_80/t01ec4801ee3cd83180.png",
                "listTag": "0",
                "price": "298",
                "uploadSting": "05-15上新",
                "tuan_flag": 0,
                "forward_url": ""
            },
            {
                "itemId": "5cdbdbe5a7d03149b3e0debf",
                "title": "摩飞 便携式充电式果汁杯榨汁机 MR9600 椰奶白",
                "stock": 999,
                "img": "https://p.ssl.qhimg.com/dr/400_400_80/t0122a80b6adb0b67b4.jpg",
                "listTag": "0",
                "tagString": "直降",
                "price": "169",
                "uploadSting": "05-15上新",
                "tuan_flag": 0,
                "forward_url": ""
            },
            {
                "itemId": "5cdbcd7df759f165ded4a488",
                "title": "Cross Humanity 家庭影院迷你音响 斗牛犬艺术蓝牙音箱低音炮 8W 黑色",
                "stock": 999,
                "img": "https://p.ssl.qhimg.com/dr/400_400_80/t01adac405500300a57.jpg",
                "listTag": "0",
                "tagString": "直降",
                "price": "429",
                "uploadSting": "05-15上新",
                "tuan_flag": 0,
                "forward_url": ""
            },
            {
                "itemId": "5cdb8d1e3f31c334e2bd668f",
                "title": "Kindle Oasis 电纸书阅读器 电子书墨水屏 7英寸wifi银灰色",
                "stock": 50,
                "img": "https://p.ssl.qhimg.com/dr/400_400_80/t0192e57692fa61d8f7.jpg",
                "listTag": "0",
                "price": "2399",
                "uploadSting": "05-15上新",
                "tuan_flag": 0,
                "forward_url": ""
            },
            {
                "itemId": "5cdb7baba7d03149b3e0de98",
                "title": "mushu木薯 蒸脸器冷热喷雾美容仪MS1601 白色",
                "stock": 999,
                "img": "https://p.ssl.qhimg.com/dr/400_400_80/t013ae1fe79b4ac4b99.jpg",
                "listTag": "0",
                "price": "499",
                "uploadSting": "05-15上新",
                "tuan_flag": 0,
                "forward_url": ""
            },
            {
                "itemId": "5cdb7a4bf759f165ded4a46f",
                "title": "mushu木薯眼唇按摩仪美眼仪 银白色MS1708",
                "stock": 999,
                "img": "https://p.ssl.qhimg.com/dr/400_400_80/t015e2670c942e076c4.jpg",
                "listTag": "0",
                "tagString": "直降",
                "price": "139",
                "uploadSting": "05-15上新",
                "tuan_flag": 0,
                "forward_url": ""
            },
            {
                "itemId": "5cdb72726792c505cc0fa038",
                "title": "mushu木薯自动起泡电动硅胶洗脸仪MS1819-湖蓝",
                "stock": 998,
                "img": "https://p.ssl.qhimg.com/dr/400_400_80/t01bf9239e1c44dae76.png",
                "listTag": "0",
                "price": "249",
                "uploadSting": "05-15上新",
                "tuan_flag": 0,
                "forward_url": ""
            },
            {
                "itemId": "5cda9bb4a7d03149b3e0de8a",
                "title": "Kindle paperwhite 电子书阅读器经典版第四代 6英寸 8G",
                "stock": 49,
                "img": "https://p.ssl.qhimg.com/dr/400_400_80/t01a70eb61b4be7a076.jpg",
                "listTag": "0",
                "price": "998",
                "uploadSting": "05-14上新",
                "tuan_flag": 0,
                "forward_url": ""
            },
            {
                "itemId": "5cda95c96792c505cc0fa031",
                "title": "Kindle 电子书阅读器 青春版 黑色 4G",
                "stock": 50,
                "img": "https://p.ssl.qhimg.com/dr/400_400_80/t01b5eb5b739020468f.jpg",
                "listTag": "0",
                "tagString": "直降",
                "price": "629",
                "uploadSting": "05-14上新",
                "tuan_flag": 0,
                "forward_url": ""
            },
            {
                "itemId": "5cda556aa7d03149b3e0de76",
                "title": "mushu木薯 电动黑头吸出仪 MS1703",
                "stock": 994,
                "img": "https://p.ssl.qhimg.com/dr/400_400_80/t019a9f2ac7a8ed0d42.jpg",
                "listTag": "0",
                "tagString": "直降",
                "price": "189",
                "uploadSting": "05-14上新",
                "tuan_flag": 0,
                "forward_url": ""
            },
            {
                "itemId": "5cd91b1da7d03149b3e0de59",
                "title": "【新品】360儿童手表M1礼盒装 薰衣草紫 6月1日起发货",
                "stock": 24,
                "img": "http://p6.qhimg.com/dr/400_400_80/t01da35ca38b555a307.png",
                "listTag": "0",
                "price": "599",
                "uploadSting": "05-13上新",
                "tuan_flag": 0,
                "forward_url": ""
            },
            {
                "itemId": "5cd7ced83f31c334e2bd665a",
                "title": "Kido儿童智能手表K3粉色",
                "stock": 5,
                "img": "http://p3.qhimg.com/dr/400_400_80/t01c5522700da63282a.png",
                "listTag": "0",
                "price": "899",
                "uploadSting": "05-12上新",
                "tuan_flag": 0,
                "forward_url": ""
            },
            {
                "itemId": "5cd7cc1aa7d03149b3e0de46",
                "title": "Kido儿童智能手表F1粉色",
                "stock": 5,
                "img": "http://p8.qhimg.com/dr/400_400_80/t01c1ad07c201948847.png",
                "listTag": "0",
                "price": "749",
                "uploadSting": "05-12上新",
                "tuan_flag": 0,
                "forward_url": ""
            },
            {
                "itemId": "5cd7cad56792c505cc0f9ff8",
                "title": "Kido儿童智能手表K2S粉色",
                "stock": 10,
                "img": "http://p5.qhimg.com/dr/400_400_80/t01a8d081d51651647a.png",
                "listTag": "0",
                "price": "599",
                "uploadSting": "05-12上新",
                "tuan_flag": 0,
                "forward_url": ""
            },
            {
                "itemId": "5cd55e24a7d03149b3e0de3b",
                "title": "Kido儿童智能手表V5 星空紫",
                "stock": 7,
                "img": "http://p4.qhimg.com/dr/400_400_80/t01c699d6deb6164af3.png",
                "listTag": "0",
                "price": "599",
                "uploadSting": "05-10上新",
                "tuan_flag": 0,
                "forward_url": ""
            },
            {
                "itemId": "5cd55b6ca7d03149b3e0de37",
                "title": "Kido儿童智能手表X3 星空灰",
                "stock": 5,
                "img": "http://p0.qhimg.com/dr/400_400_80/t0179e860fc450b4bc4.png",
                "listTag": "0",
                "price": "1399",
                "uploadSting": "05-10上新",
                "tuan_flag": 0,
                "forward_url": ""
            },
            {
                "itemId": "5cd556336792c505cc0f9ff1",
                "title": "Kido儿童智能手表B1 葡萄紫",
                "stock": 5,
                "img": "http://p9.qhimg.com/dr/400_400_80/t01e56f47c2934b6032.png",
                "listTag": "0",
                "price": "399",
                "uploadSting": "05-10上新",
                "tuan_flag": 0,
                "forward_url": ""
            },
            {
                "itemId": "5cd236fff759f165ded4a3e8",
                "title": "【新品预售】360行车记录仪 G380 发货时间6月18日",
                "stock": 439,
                "img": "http://p6.qhimg.com/dr/400_400_80/t010856038c66543311.png",
                "listTag": "0",
                "price": "499",
                "uploadSting": "05-08上新",
                "tuan_flag": 0,
                "forward_url": ""
            },
            {
                "itemId": "5cb06b353f31c3607b5387f1",
                "title": "360行车记录仪全面屏后视镜 M320",
                "stock": 169,
                "img": "https://p.ssl.qhimg.com/dr/400_400_80/t018c67e395ac123968.png",
                "listTag": "0",
                "tagString": "直降",
                "price": "349",
                "uploadSting": "04-12上新",
                "tuan_flag": 0,
                "forward_url": ""
            }
        ],
        "fallUpdateTime": "14:00已推荐更新"
    }
}